new_basic_calculator/__init__.py
new_basic_calculator/example.py
new_basic_calculator-0.1.5.dist-info/LICENSE
new_basic_calculator-0.1.5.dist-info/METADATA
new_basic_calculator-0.1.5.dist-info/WHEEL
new_basic_calculator-0.1.5.dist-info/top_level.txt
new_basic_calculator-0.1.5.dist-info/RECORD
