Metadata-Version: 2.1
Name: new_basic_calculator
Version: 0.1.5
Summary: A basic calculator SDK
Author: snowffer
Author-email: snowffer <snowffer@xxx.com>
Requires-Python: >=3.10
License-File: LICENSE
Requires-Dist: setuptools
Requires-Dist: wheel
Requires-Dist: twine
